aixm/__init__.py
aixm/utils/__init__.py
aixm/utils/local_redis.py
aixm/utils/lock.py
aixm/utils/logging.py
aixm/utils/path.py
aixm/utils/project_path.py
aixm/utils/redis_lock.py
aixm/utils/utils.py
aixm-1.1.0.dist-info/licenses/LICENSE
aixm-1.1.0.dist-info/METADATA
aixm-1.1.0.dist-info/WHEEL
aixm-1.1.0.dist-info/top_level.txt
aixm-1.1.0.dist-info/RECORD
