Metadata-Version: 2.4
Name: aixm
Version: 1.1.0
Summary: 工具包
Author: zxh
License: MIT
Project-URL: Homepage, https://github.com/zxh1993/aixm_part
Project-URL: Repository, https://github.com/zxh1993/aixm_part.git
Project-URL: Issues, https://github.com/zxh1993/aixm_part/issues
Keywords: utils,tools,utilities
Classifier: Development Status :: 5 - Production/Stable
Classifier: Intended Audience :: Developers
Classifier: Programming Language :: Python :: 3
Classifier: Programming Language :: Python :: 3.12
Classifier: Programming Language :: Python :: 3.13
Classifier: Programming Language :: Python :: 3.14
Classifier: Operating System :: OS Independent
Requires-Python: >=3.12
License-File: LICENSE
Dynamic: license-file
